kraken_ref_postalCode/__init__.py
kraken_ref_postalCode/flask_routes.py
kraken_ref_postalCode/kraken_ref_methods.py
kraken_ref_postalCode/kraken_ref_postalCode.py
kraken_ref_postalCode/kraken_ref_postalCodes.py
kraken_ref_postalCode/data/__init__.py
kraken_ref_postalCode/data/kraken_ref_postalCode.db.zip
kraken_ref_postalCode/helpers/__init__.py
kraken_ref_postalCode/helpers/json.py
kraken_ref_postalCode-0.0.4.dist-info/LICENSE.txt
kraken_ref_postalCode-0.0.4.dist-info/METADATA
kraken_ref_postalCode-0.0.4.dist-info/WHEEL
kraken_ref_postalCode-0.0.4.dist-info/top_level.txt
kraken_ref_postalCode-0.0.4.dist-info/RECORD
